Metadata-Version: 1.1
Name: graf
Version: 0.1.2
Summary: Light weight numpy, scipy, and matplotlib wrapper
Home-page: https://github.com/lambdalisue/graf
Author: Alisue
Author-email: lambdalisue@hashnote.net
License: MIT
Download-URL: https://github.com/lambdalisue/graf/tarball/master
Keywords: numpy,scipy,matplotlib,gnuplot,plot,graph,analysis
Platform: UNKNOWN
Classifier: Intended Audience :: Developers
Classifier: License :: OSI Approved :: MIT License
Classifier: Programming Language :: Python
